rf/__init__.py
rf/batch.py
rf/deconvolve.py
rf/harmonics.py
rf/imaging.py
rf/profile.py
rf/rfstream.py
rf/simple_model.py
rf/util.py
rf/data/iasp91.dat
rf/example/conf.json
rf/example/example_data.mseed
rf/example/example_events.xml
rf/example/example_inventory.xml
rf/example/minimal_example.tar.gz
rf/example/minimal_example_S.tar.gz
rf/tests/__init__.py
rf/tests/__main__.py
rf/tests/test_batch.py
rf/tests/test_deconvolve.py
rf/tests/test_harmonics.py
rf/tests/test_imaging.py
rf/tests/test_profile.py
rf/tests/test_rfstream.py
rf/tests/test_simple_model.py
rf/tests/util.py
rf-1.1.1.dist-info/LICENSE
rf-1.1.1.dist-info/METADATA
rf-1.1.1.dist-info/WHEEL
rf-1.1.1.dist-info/entry_points.txt
rf-1.1.1.dist-info/top_level.txt
rf-1.1.1.dist-info/RECORD
